robotsparse/__init__.py
robotsparse/utils/_regex.py
robotsparse/utils/exceptions.py
robotsparse/utils/parser.py
robotsparse-1.0.dist-info/LICENSE
robotsparse-1.0.dist-info/METADATA
robotsparse-1.0.dist-info/WHEEL
robotsparse-1.0.dist-info/top_level.txt
robotsparse-1.0.dist-info/RECORD
