Metadata-Version: 2.1
Name: robotsparse
Version: 1.0
Summary: A python package that enhances speed and simplicity of parsing robots files.
Home-page: https://github.com/xyzpw/robotsparse/
Author: xyzpw
Maintainer: xyzpw
License: MIT
Keywords: parsing,parser,robots,web-crawling,crawlers,crawling,sitemaps,sitemap
Classifier: Programming Language :: Python :: 3
Classifier: Programming Language :: Python :: 3.8
Classifier: Programming Language :: Python :: 3.9
Classifier: Programming Language :: Python :: 3.10
Classifier: Programming Language :: Python :: 3.11
Classifier: Topic :: Text Processing
Classifier: License :: OSI Approved :: MIT License
Classifier: Operating System :: POSIX :: Linux
Classifier: Intended Audience :: Developers
License-File: LICENSE
Requires-Dist: requests ==2.*
